bikeshare_model/VERSION
bikeshare_model/__init__.py
bikeshare_model/config.yml
bikeshare_model/pipeline.py
bikeshare_model/predict.py
bikeshare_model/train_pipeline.py
bikeshare_model/config/__init__.py
bikeshare_model/config/core.py
bikeshare_model/datasets/__init__.py
bikeshare_model/datasets/bike-rental-dataset.csv
bikeshare_model/processing/__init__.py
bikeshare_model/processing/data_manager.py
bikeshare_model/processing/features.py
bikeshare_model/processing/validation.py
bikeshare_model/trained_models/__init__.py
bikeshare_model/trained_models/bikeshare__model_output_v1.0.1.pkl
bikeshare_model-1.0.1.dist-info/METADATA
bikeshare_model-1.0.1.dist-info/WHEEL
bikeshare_model-1.0.1.dist-info/top_level.txt
bikeshare_model-1.0.1.dist-info/RECORD
